parse_schema/__init__.py
parse_schema/parse_schema.py
tests/__init__.py
tests/test.py
parse_schema-0.0.5.dist-info/METADATA
parse_schema-0.0.5.dist-info/WHEEL
parse_schema-0.0.5.dist-info/top_level.txt
parse_schema-0.0.5.dist-info/RECORD
